zyxxy2/__init__.py
zyxxy2/animation.py
zyxxy2/bbox.py
zyxxy2/canvas.py
zyxxy2/colors.py
zyxxy2/coordinates.py
zyxxy2/demo_all_shapes.py
zyxxy2/demo_shape.py
zyxxy2/demo_trigo.py
zyxxy2/docs.py
zyxxy2/examples.py
zyxxy2/files.py
zyxxy2/inspirations.txt
zyxxy2/layers.py
zyxxy2/nameless_inspirations.txt
zyxxy2/pdf.py
zyxxy2/settings.py
zyxxy2/settings_class.py
zyxxy2/shape_class.py
zyxxy2/shape_functions.py
zyxxy2/shape_style.py
zyxxy2/tests.py
zyxxy2/utils.py
zyxxy2/widgets.py
zyxxy2/word_bubbles.py
zyxxy2-0.1356951.dist-info/METADATA
zyxxy2-0.1356951.dist-info/WHEEL
zyxxy2-0.1356951.dist-info/licenses/LICENSE
zyxxy2-0.1356951.dist-info/RECORD
