Metadata-Version: 2.4
Name: zyxxy2
Version: 0.1356951
Summary: zyxxy2
Project-URL: Repository, https://github.com/yu51a5/zyxxy2
Author-email: Yulia V <yu51a5@proton.me>
License-File: LICENSE
Keywords: draw,geometrical,shapes
Classifier: Development Status :: 4 - Beta
Classifier: License :: OSI Approved :: GNU General Public License v3 or later (GPLv3+)
Classifier: Operating System :: OS Independent
Classifier: Programming Language :: Python :: 3
Requires-Python: >=3.9
Requires-Dist: matplotlib>=3.8.2
Requires-Dist: numpy>=1.26.3
Requires-Dist: pillow>=10.2.0
Requires-Dist: scipy>=1.11.4
